jqfactor_analyzer/__init__.py
jqfactor_analyzer/analyze.py
jqfactor_analyzer/attribution.py
jqfactor_analyzer/compat.py
jqfactor_analyzer/config.json
jqfactor_analyzer/data.py
jqfactor_analyzer/exceptions.py
jqfactor_analyzer/factor_cache.py
jqfactor_analyzer/performance.py
jqfactor_analyzer/plot_utils.py
jqfactor_analyzer/plotting.py
jqfactor_analyzer/prepare.py
jqfactor_analyzer/preprocess.py
jqfactor_analyzer/sample.py
jqfactor_analyzer/utils.py
jqfactor_analyzer/version.py
jqfactor_analyzer/when.py
jqfactor_analyzer/sample_data/VOL5.csv
jqfactor_analyzer/sample_data/index_weight_info.csv
jqfactor_analyzer/sample_data/weight_info.csv
jqfactor_analyzer-1.1.0.dist-info/LICENSE
jqfactor_analyzer-1.1.0.dist-info/METADATA
jqfactor_analyzer-1.1.0.dist-info/WHEEL
jqfactor_analyzer-1.1.0.dist-info/top_level.txt
jqfactor_analyzer-1.1.0.dist-info/RECORD
