Metadata-Version: 2.1
Name: jqfactor-analyzer
Version: 1.1.0
Summary: JoinQuant single factor analyzer
Home-page: https://www.joinquant.com
Author: JoinQuant
Author-email: xlx@joinquant.com
License: Apache License v2
Platform: all
Classifier: Programming Language :: Python
Classifier: Operating System :: Microsoft :: Windows
Classifier: Operating System :: Unix
Classifier: Programming Language :: Python :: 2.7
Classifier: Programming Language :: Python :: 3.4
Classifier: Programming Language :: Python :: 3.5
Classifier: Programming Language :: Python :: 3.6
Classifier: Programming Language :: Python :: 3.7
Requires-Dist: six
Requires-Dist: fastcache (>=1.0.2)
Requires-Dist: SQLAlchemy (>=1.2.8)
Requires-Dist: cached-property (>=1.5.1)
Requires-Dist: statsmodels
Requires-Dist: scipy
Requires-Dist: numpy (>=1.15.0)
Requires-Dist: pandas (>=1.0.0)
Requires-Dist: matplotlib
Requires-Dist: seaborn
Requires-Dist: jqdatasdk
Requires-Dist: pyarrow
